jinja2_github.py
jinja2_github-0.1.1.dist-info/LICENSE
jinja2_github-0.1.1.dist-info/WHEEL
jinja2_github-0.1.1.dist-info/METADATA
jinja2_github-0.1.1.dist-info/RECORD
